[
  {
    "avatar": "https://avatars2.githubusercontent.com/u/905434?s=460&v=4",
    "name": "Ruan Yifeng",
    "introduction": "focusing on web technology",
    "url": "http://www.ruanyifeng.com/home.html",
    "title": "go go go"
  },
  {
    "avatar": "https://avatars3.githubusercontent.com/u/4979648?s=180&v=4",
    "name": "纯洁的微笑",
    "introduction": "programmer",
    "url": "http://www.ityouknow.com/",
    "title": "go go go"
  },
  {
    "avatar": "https://avatars3.githubusercontent.com/u/10127059?s=460&v=4",
    "name": "Ghost Stories",
    "introduction": "programmer",
    "url": "http://wangnan.tech/all-tags/",
    "title": "go go go"
  },
  {
    "avatar": "https://avatars1.githubusercontent.com/u/470058?s=460&v=4",
    "name": "廖雪峰",
    "introduction": "programmer",
    "url": "https://www.liaoxuefeng.com/",
    "title": "go go go"
  }
]
